deepfolio/__init__.py
deepfolio/backtester.py
deepfolio/train.py
deepfolio/data/__init__.py
deepfolio/data/data_loader.py
deepfolio/models/__init__.py
deepfolio/models/deep_learning_layer.py
deepfolio/models/diffopt_portfolio.py
deepfolio/models/factor_model.py
deepfolio/models/feature_extractor.py
deepfolio/models/merge_layer.py
deepfolio/models/parameter_predictor.py
deepfolio/models/qp_layer.py
deepfolio/optimizers/__init__.py
deepfolio/optimizers/black_litterman_optimization.py
deepfolio/optimizers/custom_optimizer.py
deepfolio/optimizers/cvar_optimization.py
deepfolio/optimizers/factor_neutral_optimization.py
deepfolio/optimizers/hierarchical_risk_parity.py
deepfolio/optimizers/multi_period_optimization.py
deepfolio/optimizers/realtime_optimizer.py
deepfolio/optimizers/rl_dynamic_allocation.py
deepfolio/optimizers/robust_optimization.py
deepfolio/optimizers/sentiment_analysis.py
deepfolio/solvers/__init__.py
deepfolio/solvers/solvers.py
deepfolio/utils/__init__.py
deepfolio/utils/hyperparamater_tuning.py
deepfolio/utils/metrics.py
deepfolio/utils/risk_management.py
deepfolio/utils/visualization.py
tests/__init__.py
tests/test_distance/__init__.py
tests/test_distance/test_distance.py
tests/test_measures/__init__.py
tests/test_measures/test_measures.py
tests/test_model_selection/__init__.py
tests/test_model_selection/test_combinatorial.py
tests/test_model_selection/test_validation.py
tests/test_model_selection/test_walk_forward.py
tests/test_optimization/__init__.py
tests/test_optimization/test_cluster/__init__.py
tests/test_optimization/test_cluster/test_herc.py
tests/test_optimization/test_cluster/test_hrp.py
tests/test_optimization/test_cluster/test_nco.py
tests/test_optimization/test_ensemble/__init__.py
tests/test_optimization/test_ensemble/test_stacking.py
tests/test_optimization/test_naive/__init__.py
tests/test_optimization/test_naive/test_naive.py
tests/test_portfolio/__init__.py
tests/test_portfolio/test_multi_period_portfolio.py
deepfolio-1.3.0.dist-info/LICENSE
deepfolio-1.3.0.dist-info/METADATA
deepfolio-1.3.0.dist-info/WHEEL
deepfolio-1.3.0.dist-info/top_level.txt
deepfolio-1.3.0.dist-info/RECORD
