Metadata-Version: 2.1
Name: deepfolio
Version: 1.3.0
Summary: Python Deep Learning Library for Real-time Portfolio Optimization
Home-page: https://github.com/jialuechen/deepfolio
Author: Jialue Chen
Author-email: jialuechen@outlook.com
License: BSD-2
License-File: LICENSE
